README.md
setup.py
neptune_dnsoverhttps_protocol/__init__.py
neptune_dnsoverhttps_protocol/connect.py
neptune_dnsoverhttps_protocol/protocol.py
neptune_dnsoverhttps_protocol.egg-info/PKG-INFO
neptune_dnsoverhttps_protocol.egg-info/SOURCES.txt
neptune_dnsoverhttps_protocol.egg-info/dependency_links.txt
neptune_dnsoverhttps_protocol.egg-info/requires.txt
neptune_dnsoverhttps_protocol.egg-info/top_level.txt